cheme_toolkit-0.1.0.dist-info/licenses/LICENSE
chemetk/__init__.py
cheme_toolkit-0.1.0.dist-info/METADATA
cheme_toolkit-0.1.0.dist-info/WHEEL
cheme_toolkit-0.1.0.dist-info/top_level.txt
cheme_toolkit-0.1.0.dist-info/RECORD
