Metadata-Version: 2.4
Name: cheme-toolkit
Version: 0.1.0
Summary: cheme-toolkit 是一个为化学工程计算设计的工具包，提供了气液平衡数据处理、精馏塔计算、热力学性质计算、可视化绘图以及 Web 应用等功能，方便化学工程相关的计算与模拟工作。
Author-email: Grtresy <ssk23@mails.tsinghua.edu.cn>
License:                     GNU GENERAL PUBLIC LICENSE
Project-URL: Repository, https://github.com/Grtresy/chemetk
Requires-Python: >=3.11
License-File: LICENSE
Requires-Dist: dash>=3.2.0
Requires-Dist: matplotlib>=3.10.7
Requires-Dist: notebook>=7.4.7
Requires-Dist: numpy>=2.3.3
Requires-Dist: pandas>=2.3.3
Requires-Dist: scipy>=1.16.2
Dynamic: license-file
